{"version": 0.6, "generator": "Overpass API 0.7.62.8 e802775f", "osm3s": {"timestamp_osm_base": "2025-09-04T16:22:28Z", "copyright": "The data included in this document is from www.openstreetmap.org. The data is made available under ODbL."}, "elements": [{"type": "node", "id": 321260475, "lat": -32.6847704, "lon": -52.6104597}, {"type": "node", "id": 321260483, "lat": -32.6855334, "lon": -52.6116266}, {"type": "node", "id": 321260485, "lat": -32.6867234, "lon": -52.6129086}, {"type": "node", "id": 321260487, "lat": -32.6877705, "lon": -52.6137087}, {"type": "node", "id": 321260488, "lat": -32.7211885, "lon": -52.6331566}, {"type": "node", "id": 321260496, "lat": -32.7281075, "lon": -52.6371087}, {"type": "node", "id": 321260498, "lat": -32.7768875, "lon": -52.6608716}, {"type": "node", "id": 321260500, "lat": -32.7794274, "lon": -52.6621847}, {"type": "node", "id": 321260501, "lat": -32.7819475, "lon": -52.6637586}, {"type": "node", "id": 321260502, "lat": -32.8096925, "lon": -52.6829547}, {"type": "node", "id": 321260503, "lat": -32.8124174, "lon": -52.6847397}, {"type": "node", "id": 321260507, "lat": -32.8149155, "lon": -52.6860936}, {"type": "node", "id": 321260509, "lat": -32.8466434, "lon": -52.7000917}, {"type": "node", "id": 321260510, "lat": -32.8491324, "lon": -52.7012986}, {"type": "node", "id": 321260511, "lat": -32.9050135, "lon": -52.7319846}, {"type": "node", "id": 321260512, "lat": -32.9065724, "lon": -52.7328896}, {"type": "node", "id": 321260513, "lat": -32.9080504, "lon": -52.7339767}, {"type": "node", "id": 321260514, "lat": -32.9096784, "lon": -52.7355017}, {"type": "node", "id": 321260515, "lat": -32.9360135, "lon": -52.7630397}, {"type": "node", "id": 321260516, "lat": -32.9384601, "lon": -52.7654835}, {"type": "node", "id": 321260517, "lat": -32.9577684, "lon": -52.7825287}, {"type": "node", "id": 321260518, "lat": -33.0263241, "lon": -52.849465}, {"type": "node", "id": 321260519, "lat": -33.0320135, "lon": -52.8549367}, {"type": "node", "id": 321260520, "lat": -33.0594355, "lon": -52.8778566}, {"type": "node", "id": 321260521, "lat": -33.1119924, "lon": -52.9259517}, {"type": "node", "id": 321260536, "lat": -33.1138835, "lon": -52.9277497}, {"type": "node", "id": 321260539, "lat": -33.1153905, "lon": -52.9294497}, {"type": "node", "id": 321260541, "lat": -33.1272755, "lon": -52.9468497}, {"type": "node", "id": 321260543, "lat": -33.1285775, "lon": -52.9485887}, {"type": "node", "id": 321260544, "lat": -33.1987664, "lon": -53.0307403}, {"type": "node", "id": 321260545, "lat": -33.2000973, "lon": -53.0322397}, {"type": "node", "id": 321260546, "lat": -33.2013766, "lon": -53.0334091}, {"type": "node", "id": 2665850568, "lat": -32.6778202, "lon": -52.5972903}, {"type": "node", "id": 2665850570, "lat": -32.8521542, "lon": -52.7029575}, {"type": "node", "id": 2665850586, "lat": -32.852615, "lon": -52.7032104}, {"type": "node", "id": 2665850606, "lat": -32.8536625, "lon": -52.7037855}, {"type": "node", "id": 2665850614, "lat": -32.8542123, "lon": -52.7040873}, {"type": "node", "id": 2665850615, "lat": -32.93995, "lon": -52.7667614, "tags": {"highway": "speed_camera", "maxspeed": "60"}}, {"type": "node", "id": 3372673786, "lat": -33.179917, "lon": -53.0086533}, {"type": "node", "id": 3372673806, "lat": -33.1604899, "lon": -52.9859082}, {"type": "node", "id": 3372676348, "lat": -32.9825107, "lon": -52.739549}, {"type": "node", "id": 3372676349, "lat": -32.9881906, "lon": -52.7415589}, {"type": "node", "id": 3372676350, "lat": -32.9890418, "lon": -52.742359}, {"type": "node", "id": 3372676351, "lat": -32.9903512, "lon": -52.7452862}, {"type": "node", "id": 3372676352, "lat": -32.9967181, "lon": -52.7512575}, {"type": "node", "id": 3372676353, "lat": -32.9988784, "lon": -52.7529943}, {"type": "node", "id": 3372676354, "lat": -32.9993858, "lon": -52.7536773}, {"type": "node", "id": 3372676355, "lat": -33.0010387, "lon": -52.7560385}, {"type": "node", "id": 3372676356, "lat": -33.0024135, "lon": -52.759395}, {"type": "node", "id": 3372676357, "lat": -33.0042464, "lon": -52.7627319}, {"type": "node", "id": 3372676358, "lat": -33.0045901, "lon": -52.7631417}, {"type": "node", "id": 3372676359, "lat": -33.0090413, "lon": -52.7706742}, {"type": "node", "id": 3372676360, "lat": -33.0110213, "lon": -52.7742063}, {"type": "node", "id": 3372676361, "lat": -33.0125759, "lon": -52.7777969}, {"type": "node", "id": 3372676362, "lat": -32.998011, "lon": -52.8002188}, {"type": "node", "id": 3372676363, "lat": -32.9893962, "lon": -52.8134029}, {"type": "node", "id": 3372689493, "lat": -32.9814185, "lon": -52.7394737}, {"type": "node", "id": 3372689494, "lat": -32.9776649, "lon": -52.7371546}, {"type": "node", "id": 3372689495, "lat": -32.9757568, "lon": -52.7355024}, {"type": "node", "id": 3372689496, "lat": -32.9736867, "lon": -52.7343651}, {"type": "node", "id": 3372689497, "lat": -32.9727686, "lon": -52.7338287}, {"type": "node", "id": 3372689498, "lat": -32.9629933, "lon": -52.7260825}, {"type": "node", "id": 3372689499, "lat": -32.9626512, "lon": -52.7259966}, {"type": "node", "id": 3372689500, "lat": -32.9590684, "lon": -52.7235719}, {"type": "node", "id": 3372689501, "lat": -32.953703, "lon": -52.7235934}, {"type": "node", "id": 3372689502, "lat": -32.9460324, "lon": -52.7193448}, {"type": "node", "id": 3372689503, "lat": -32.9446098, "lon": -52.7178427}, {"type": "node", "id": 3372689504, "lat": -32.9406842, "lon": -52.7152893}, {"type": "node", "id": 3372689505, "lat": -32.9329764, "lon": -52.7079507}, {"type": "node", "id": 3372689506, "lat": -32.9309593, "lon": -52.7058908}, {"type": "node", "id": 3372689507, "lat": -32.9264927, "lon": -52.7099892}, {"type": "node", "id": 3372689511, "lat": -32.9243854, "lon": -52.7107617}, {"type": "node", "id": 3372689512, "lat": -32.9161178, "lon": -52.7281424}, {"type": "node", "id": 3372689513, "lat": -32.9124431, "lon": -52.735953}, {"type": "node", "id": 3372689514, "lat": -32.91172, "lon": -52.7376362}, {"type": "node", "id": 3372689515, "lat": -32.9432593, "lon": -52.7701565}, {"type": "node", "id": 3372689516, "lat": -32.9382531, "lon": -52.7657148}, {"type": "node", "id": 3372689517, "lat": -32.938163, "lon": -52.7658864}, {"type": "node", "id": 3372689518, "lat": -32.9387753, "lon": -52.7671954}, {"type": "node", "id": 3372689519, "lat": -32.9390815, "lon": -52.7675387}, {"type": "node", "id": 3372689520, "lat": -32.942557, "lon": -52.7723237}, {"type": "node", "id": 3372689521, "lat": -32.9093267, "lon": -52.801077}, {"type": "node", "id": 3372689541, "lat": -32.9366983, "lon": -52.7637237}, {"type": "node", "id": 3372689542, "lat": -32.9368304, "lon": -52.7635261}, {"type": "node", "id": 3372689543, "lat": -32.9367944, "lon": -52.7632257}, {"type": "node", "id": 3372689544, "lat": -32.9336788, "lon": -52.7576467}, {"type": "node", "id": 3372689545, "lat": -32.9334086, "lon": -52.7569601}, {"type": "node", "id": 3372689546, "lat": -32.9332466, "lon": -52.7530333}, {"type": "node", "id": 3372689547, "lat": -32.9331205, "lon": -52.752926}, {"type": "node", "id": 3372689548, "lat": -32.9326342, "lon": -52.752926}, {"type": "node", "id": 3372689549, "lat": -32.9317518, "lon": -52.7520892}, {"type": "node", "id": 3372689550, "lat": -32.930311, "lon": -52.7521321}, {"type": "node", "id": 3372689551, "lat": -32.928219, "lon": -52.7548883}, {"type": "node", "id": 3372689552, "lat": -32.951596, "lon": -52.7770665}, {"type": "node", "id": 3372689553, "lat": -32.9590144, "lon": -52.7627322}, {"type": "node", "id": 3372689554, "lat": -32.94324, "lon": -52.7696725}, {"type": "node", "id": 3372689561, "lat": -32.9660225, "lon": -52.7905851}, {"type": "node", "id": 3372689574, "lat": -32.9847266, "lon": -52.8088439}, {"type": "node", "id": 3372689645, "lat": -33.110654, "lon": -52.9247266}, {"type": "node", "id": 3372692664, "lat": -32.8694087, "lon": -52.7144247}, {"type": "node", "id": 3372692665, "lat": -32.8661852, "lon": -52.711774}, {"type": "node", "id": 3372692666, "lat": -32.8663286, "lon": -52.7110503}, {"type": "node", "id": 3372692667, "lat": -32.8695999, "lon": -52.7128717}, {"type": "node", "id": 3372692668, "lat": -32.8663825, "lon": -52.7107691}, {"type": "node", "id": 3372692669, "lat": -32.8564116, "lon": -52.7055864}, {"type": "node", "id": 3372692670, "lat": -32.8553051, "lon": -52.7050822}, {"type": "node", "id": 3372692671, "lat": -32.854827, "lon": -52.7049196}, {"type": "node", "id": 3372692672, "lat": -32.8543625, "lon": -52.704635}, {"type": "node", "id": 3372692673, "lat": -32.854144, "lon": -52.7042935}, {"type": "node", "id": 3372692674, "lat": -32.7900945, "lon": -52.6693947}, {"type": "node", "id": 3372692675, "lat": -32.7899253, "lon": -52.6698092}, {"type": "node", "id": 3372692676, "lat": -32.7931652, "lon": -52.6721509}, {"type": "node", "id": 3372692677, "lat": -32.7900894, "lon": -52.6880062}, {"type": "node", "id": 3372692678, "lat": -32.7896929, "lon": -52.6887055}, {"type": "node", "id": 3372692679, "lat": -32.7896929, "lon": -52.6894535}, {"type": "node", "id": 3372692680, "lat": -32.7883395, "lon": -52.6962835}, {"type": "node", "id": 3372695626, "lat": -32.6828672, "lon": -52.606832}, {"type": "node", "id": 3372695638, "lat": -32.7882179, "lon": -52.6680964}, {"type": "node", "id": 3372695653, "lat": -32.8256119, "lon": -52.6576841}, {"type": "node", "id": 3372695658, "lat": -32.8253112, "lon": -52.6615382}, {"type": "node", "id": 3372695659, "lat": -32.8235757, "lon": -52.6680429}, {"type": "node", "id": 3372695660, "lat": -32.824218, "lon": -52.6757023}, {"type": "node", "id": 3372695661, "lat": -32.8267187, "lon": -52.681085}, {"type": "node", "id": 3372695662, "lat": -32.8242418, "lon": -52.6902078}, {"type": "node", "id": 3372700358, "lat": -33.1638747, "lon": -52.9898672}, {"type": "node", "id": 3372700359, "lat": -33.1630303, "lon": -52.9888796}, {"type": "node", "id": 3372700362, "lat": -33.1649765, "lon": -52.9911561}, {"type": "node", "id": 3372701295, "lat": -33.1293497, "lon": -52.9494915}, {"type": "node", "id": 3372701333, "lat": -33.1050365, "lon": -52.9195847}, {"type": "node", "id": 3372701342, "lat": -33.0481206, "lon": -52.8683985}, {"type": "node", "id": 3373306328, "lat": -32.8076702, "lon": -53.1162218}, {"type": "node", "id": 3373306329, "lat": -32.809029, "lon": -53.1173996}, {"type": "node", "id": 3373306330, "lat": -32.8139073, "lon": -53.1185038}, {"type": "node", "id": 3373306331, "lat": -32.8181113, "lon": -53.1194444}, {"type": "node", "id": 3373306332, "lat": -32.8218801, "lon": -53.1218262}, {"type": "node", "id": 3373306333, "lat": -32.8287681, "lon": -53.121397}, {"type": "node", "id": 3373306334, "lat": -32.8387566, "lon": -53.1222124}, {"type": "node", "id": 3373306335, "lat": -32.8483654, "lon": -53.1212683}, {"type": "node", "id": 3373306336, "lat": -32.8533767, "lon": -53.1209679}, {"type": "node", "id": 3373306337, "lat": -32.8580092, "lon": -53.1219764}, {"type": "node", "id": 3373306338, "lat": -32.8584418, "lon": -53.1218047}, {"type": "node", "id": 3373306339, "lat": -32.8588924, "lon": -53.1218691}, {"type": "node", "id": 3373306340, "lat": -32.8593791, "lon": -53.1223412}, {"type": "node", "id": 3373306341, "lat": -32.8597756, "lon": -53.1222554}, {"type": "node", "id": 3373306342, "lat": -32.8600099, "lon": -53.1217833}, {"type": "node", "id": 3373306343, "lat": -32.860046, "lon": -53.1207533}, {"type": "node", "id": 3373306344, "lat": -32.8626282, "lon": -53.1136801}, {"type": "node", "id": 3373306345, "lat": -32.8641602, "lon": -53.1093885}, {"type": "node", "id": 3373306346, "lat": -32.8652416, "lon": -53.1074359}, {"type": "node", "id": 3373306347, "lat": -32.8670619, "lon": -53.1032731}, {"type": "node", "id": 3373306348, "lat": -32.8679631, "lon": -53.1020286}, {"type": "node", "id": 3373306349, "lat": -32.8746493, "lon": -53.1016423}, {"type": "node", "id": 3373306350, "lat": -32.8785418, "lon": -53.100033}, {"type": "node", "id": 3373306351, "lat": -32.8828847, "lon": -53.1006553}, {"type": "node", "id": 3373306352, "lat": -32.886921, "lon": -53.0992391}, {"type": "node", "id": 3373306353, "lat": -32.8871926, "lon": -53.0975515}, {"type": "node", "id": 3373306354, "lat": -32.8857678, "lon": -53.0957629}, {"type": "node", "id": 3373306355, "lat": -32.8915878, "lon": -53.0699493}, {"type": "node", "id": 3373306356, "lat": -32.8872973, "lon": -53.0654267}, {"type": "node", "id": 3373306367, "lat": -32.8841348, "lon": -53.064261}, {"type": "node", "id": 3373306368, "lat": -32.8870845, "lon": -53.0654159}, {"type": "node", "id": 3373306369, "lat": -32.8876104, "lon": -53.0649894}, {"type": "node", "id": 3373306370, "lat": -32.8891623, "lon": -53.0585977}, {"type": "node", "id": 3373306371, "lat": -32.8893391, "lon": -53.0584824}, {"type": "node", "id": 3373306372, "lat": -32.8952106, "lon": -53.0604284}, {"type": "node", "id": 3373306379, "lat": -32.9114089, "lon": -53.0656721}, {"type": "node", "id": 3373306380, "lat": -32.9252921, "lon": -53.0681263}, {"type": "node", "id": 3373306381, "lat": -32.9260656, "lon": -53.0685818}, {"type": "node", "id": 3373306382, "lat": -32.9301179, "lon": -53.0734527}, {"type": "node", "id": 3373306383, "lat": -32.9341205, "lon": -53.0796102}, {"type": "node", "id": 3373306384, "lat": -32.9412744, "lon": -53.0871901}, {"type": "node", "id": 3373306385, "lat": -32.9426892, "lon": -53.0917995}, {"type": "node", "id": 3373306386, "lat": -32.946635, "lon": -53.0966918}, {"type": "node", "id": 3373306387, "lat": -32.9508732, "lon": -53.1009083}, {"type": "node", "id": 3373306388, "lat": -32.9557448, "lon": -53.1040612}, {"type": "node", "id": 3373306389, "lat": -32.9586413, "lon": -53.1052548}, {"type": "node", "id": 3373306390, "lat": -32.9609976, "lon": -53.1049544}, {"type": "node", "id": 3373306391, "lat": -32.9757799, "lon": -53.1034935}, {"type": "node", "id": 3373306392, "lat": -32.9955335, "lon": -53.0974361}, {"type": "node", "id": 3373306593, "lat": -32.9980081, "lon": -53.0969131}, {"type": "node", "id": 3373306594, "lat": -33.0009572, "lon": -53.0968782}, {"type": "node", "id": 3373306650, "lat": -33.055405, "lon": -53.2010357}, {"type": "node", "id": 3373306651, "lat": -33.0541174, "lon": -53.2005899}, {"type": "node", "id": 3373306652, "lat": -33.0517467, "lon": -53.1990543}, {"type": "node", "id": 3373306653, "lat": -33.0499167, "lon": -53.1987056}, {"type": "node", "id": 3373306654, "lat": -33.040305, "lon": -53.1938428}, {"type": "node", "id": 3373306655, "lat": -33.032453, "lon": -53.1822744}, {"type": "node", "id": 3373306656, "lat": -33.0261746, "lon": -53.1804666}, {"type": "node", "id": 3373306657, "lat": -33.0244092, "lon": -53.1802735}, {"type": "node", "id": 3373306658, "lat": -33.016016, "lon": -53.1752819}, {"type": "node", "id": 3373306659, "lat": -33.008767, "lon": -53.1702071}, {"type": "node", "id": 3373306660, "lat": -33.0002553, "lon": -53.16517}, {"type": "node", "id": 3373306661, "lat": -32.9913334, "lon": -53.1620854}, {"type": "node", "id": 3373306662, "lat": -32.9827819, "lon": -53.1591082}, {"type": "node", "id": 3373306663, "lat": -32.9772851, "lon": -53.154484}, {"type": "node", "id": 3373306664, "lat": -32.9678496, "lon": -53.1441084}, {"type": "node", "id": 3373306665, "lat": -32.9654147, "lon": -53.1432985}, {"type": "node", "id": 3373306666, "lat": -32.9537886, "lon": -53.1355951}, {"type": "node", "id": 3373306667, "lat": -32.9511192, "lon": -53.1331812}, {"type": "node", "id": 3373306668, "lat": -32.9472468, "lon": -53.1309202}, {"type": "node", "id": 3373306669, "lat": -32.9063142, "lon": -53.1116525}, {"type": "node", "id": 3373306670, "lat": -32.8983895, "lon": -53.104206}, {"type": "node", "id": 3373306671, "lat": -32.8923826, "lon": -53.1026308}, {"type": "node", "id": 3373306672, "lat": -32.8916173, "lon": -53.1026691}, {"type": "node", "id": 3373306688, "lat": -33.1526983, "lon": -52.9767952}, {"type": "node", "id": 3459365240, "lat": -33.0488487, "lon": -52.8690071}, {"type": "node", "id": 3534112857, "lat": -32.6240598, "lon": -53.1919981}, {"type": "node", "id": 3534112858, "lat": -32.624457, "lon": -53.1906971}, {"type": "node", "id": 3534112859, "lat": -32.6320033, "lon": -53.1721911}, {"type": "node", "id": 3534112860, "lat": -32.6336193, "lon": -53.1647594}, {"type": "node", "id": 3534112861, "lat": -32.6364266, "lon": -53.1553276}, {"type": "node", "id": 3534112864, "lat": -32.6177758, "lon": -53.1914974}, {"type": "node", "id": 3534112865, "lat": -32.5909944, "lon": -53.1696085}, {"type": "node", "id": 3534112866, "lat": -32.5910848, "lon": -53.1693725}, {"type": "node", "id": 3534112867, "lat": -32.5950079, "lon": -53.1662611}, {"type": "node", "id": 3623819165, "lat": -32.5135846, "lon": -53.0624812}, {"type": "node", "id": 3623819168, "lat": -32.5184211, "lon": -53.060971}, {"type": "node", "id": 3623819169, "lat": -32.5195589, "lon": -53.2177279}, {"type": "node", "id": 3623819173, "lat": -32.5248875, "lon": -53.0621951}, {"type": "node", "id": 3623819174, "lat": -32.5258402, "lon": -53.0613378}, {"type": "node", "id": 3623819175, "lat": -32.5326077, "lon": -53.058922}, {"type": "node", "id": 3623819177, "lat": -32.5369058, "lon": -53.0441813}, {"type": "node", "id": 3623819180, "lat": -32.5412725, "lon": -53.0439058}, {"type": "node", "id": 3623819182, "lat": -32.5476708, "lon": -53.0413293}, {"type": "node", "id": 3623819185, "lat": -32.5502983, "lon": -53.0412319}, {"type": "node", "id": 3623819186, "lat": -32.5528935, "lon": -53.0403754}, {"type": "node", "id": 3623819187, "lat": -32.5535786, "lon": -53.0403891}, {"type": "node", "id": 3623819188, "lat": -32.5551578, "lon": -53.0400585}, {"type": "node", "id": 4077294577, "lat": -32.8564711, "lon": -52.7053274}, {"type": "node", "id": 4077294578, "lat": -32.8567632, "lon": -52.7046636}, {"type": "node", "id": 4077294579, "lat": -32.8568562, "lon": -52.7040625}, {"type": "node", "id": 4077294580, "lat": -32.857494, "lon": -52.7030819}, {"type": "node", "id": 4077294581, "lat": -32.8582513, "lon": -52.7024334}, {"type": "node", "id": 4077294582, "lat": -32.8585968, "lon": -52.7011996}, {"type": "node", "id": 4077294583, "lat": -32.8589688, "lon": -52.7010889}, {"type": "node", "id": 4077294584, "lat": -32.8596331, "lon": -52.6975142}, {"type": "node", "id": 4077294690, "lat": -32.8289285, "lon": -52.6922754}, {"type": "node", "id": 4077294701, "lat": -32.8538497, "lon": -52.7038883}, {"type": "node", "id": 4085213002, "lat": -32.8606686, "lon": -52.7076319}, {"type": "node", "id": 4085213003, "lat": -32.8605743, "lon": -52.7078798}, {"type": "node", "id": 4085213004, "lat": -32.8550509, "lon": -52.7169011}, {"type": "node", "id": 4085213005, "lat": -32.8715294, "lon": -52.7138859}, {"type": "node", "id": 4085213006, "lat": -32.8736908, "lon": -52.7151439}, {"type": "node", "id": 4085213007, "lat": -32.8743279, "lon": -52.7153743}, {"type": "node", "id": 4085213008, "lat": -32.8756748, "lon": -52.716229}, {"type": "node", "id": 4085213009, "lat": -32.8765377, "lon": -52.7165363}, {"type": "node", "id": 4085213010, "lat": -32.8835295, "lon": -52.7205501}, {"type": "node", "id": 4085213011, "lat": -32.8791827, "lon": -52.7177977}, {"type": "node", "id": 4085213039, "lat": -32.8736795, "lon": -52.7147758}, {"type": "node", "id": 4092595713, "lat": -32.9677782, "lon": -52.7459896}, {"type": "node", "id": 4107772059, "lat": -32.99704, "lon": -52.8208662}, {"type": "node", "id": 4107772060, "lat": -32.9960279, "lon": -52.8246361}, {"type": "node", "id": 4107772061, "lat": -32.9938614, "lon": -52.8324142}, {"type": "node", "id": 4107772062, "lat": -32.9918559, "lon": -52.8394721}, {"type": "node", "id": 4107772063, "lat": -32.9901323, "lon": -52.8456178}, {"type": "node", "id": 4107772064, "lat": -32.9881509, "lon": -52.8526757}, {"type": "node", "id": 4107772065, "lat": -32.9878448, "lon": -52.8537416}, {"type": "node", "id": 4107772066, "lat": -32.9877965, "lon": -52.853924}, {"type": "node", "id": 4107772067, "lat": -32.9877804, "lon": -52.85402}, {"type": "node", "id": 4107772068, "lat": -32.9878368, "lon": -52.8541065}, {"type": "node", "id": 4107772069, "lat": -32.9882959, "lon": -52.8545386}, {"type": "node", "id": 4107772070, "lat": -32.9911632, "lon": -52.8573041}, {"type": "node", "id": 4107772071, "lat": -32.9960842, "lon": -52.8620478}, {"type": "node", "id": 4107772072, "lat": -32.9973648, "lon": -52.8632481}, {"type": "node", "id": 4107772073, "lat": -32.9974614, "lon": -52.8633537}, {"type": "node", "id": 4107772074, "lat": -32.9975017, "lon": -52.863469}, {"type": "node", "id": 4107772075, "lat": -32.9974856, "lon": -52.8635938}, {"type": "node", "id": 4107772076, "lat": -32.9969379, "lon": -52.8648229}, {"type": "node", "id": 4107772077, "lat": -32.993515, "lon": -52.8726586}, {"type": "node", "id": 4107772078, "lat": -32.9896329, "lon": -52.8816274}, {"type": "node", "id": 4107772079, "lat": -32.9892383, "lon": -52.8824917}, {"type": "node", "id": 4107772080, "lat": -32.9889403, "lon": -52.8832791}, {"type": "node", "id": 4107772081, "lat": -32.9881187, "lon": -52.8855357}, {"type": "node", "id": 4107772082, "lat": -32.9876918, "lon": -52.886592}, {"type": "node", "id": 4107772083, "lat": -32.9875307, "lon": -52.8870721}, {"type": "node", "id": 4107772084, "lat": -32.9874099, "lon": -52.8875138}, {"type": "node", "id": 4107772085, "lat": -32.9862742, "lon": -52.8905866}, {"type": "node", "id": 4107772086, "lat": -32.983737, "lon": -52.8976349}, {"type": "node", "id": 4107772087, "lat": -32.9804505, "lon": -52.9065941}, {"type": "node", "id": 4107772088, "lat": -32.9759234, "lon": -52.9190103}, {"type": "node", "id": 4107772289, "lat": -32.9738208, "lon": -52.924791}, {"type": "node", "id": 4107772290, "lat": -32.9733053, "lon": -52.9261642}, {"type": "node", "id": 4107772291, "lat": -32.9732247, "lon": -52.9264235}, {"type": "node", "id": 4107772292, "lat": -32.9732005, "lon": -52.9265867}, {"type": "node", "id": 4107772293, "lat": -32.9732247, "lon": -52.9266827}, {"type": "node", "id": 4107772357, "lat": -32.9733797, "lon": -52.9266652}, {"type": "node", "id": 4107772358, "lat": -32.9734971, "lon": -52.9266418}, {"type": "node", "id": 4107772359, "lat": -32.9736976, "lon": -52.926671}, {"type": "node", "id": 4107772360, "lat": -32.9744019, "lon": -52.9268167}, {"type": "node", "id": 4107772361, "lat": -32.9759277, "lon": -52.9271024}, {"type": "node", "id": 4107772362, "lat": -32.9766564, "lon": -52.9272481}, {"type": "node", "id": 4107772363, "lat": -32.9768423, "lon": -52.9272948}, {"type": "node", "id": 4107772364, "lat": -32.9769743, "lon": -52.9273706}, {"type": "node", "id": 4107772365, "lat": -32.977209, "lon": -52.9274463}, {"type": "node", "id": 4107772366, "lat": -32.9785832, "lon": -52.9277611}, {"type": "node", "id": 4107772367, "lat": -32.9786957, "lon": -52.9277728}, {"type": "node", "id": 4107772368, "lat": -32.9788229, "lon": -52.9277845}, {"type": "node", "id": 4107772369, "lat": -32.9789109, "lon": -52.927802}, {"type": "node", "id": 4107772370, "lat": -32.9789843, "lon": -52.9278194}, {"type": "node", "id": 4107772371, "lat": -32.979219, "lon": -52.9278719}, {"type": "node", "id": 4107772372, "lat": -32.9793853, "lon": -52.9279069}, {"type": "node", "id": 4107772373, "lat": -32.979532, "lon": -52.9279127}, {"type": "node", "id": 4107772374, "lat": -32.9797863, "lon": -52.927936}, {"type": "node", "id": 4107772375, "lat": -32.9804562, "lon": -52.9280818}, {"type": "node", "id": 4107772376, "lat": -32.9812485, "lon": -52.9283033}, {"type": "node", "id": 4107772377, "lat": -32.9846813, "lon": -52.9290495}, {"type": "node", "id": 4107772378, "lat": -32.9849845, "lon": -52.9291428}, {"type": "node", "id": 4107772379, "lat": -32.9850677, "lon": -52.9291603}, {"type": "node", "id": 4107772380, "lat": -32.9852437, "lon": -52.9291603}, {"type": "node", "id": 4107772381, "lat": -32.9854051, "lon": -52.9291778}, {"type": "node", "id": 4107772382, "lat": -32.9855567, "lon": -52.9292186}, {"type": "node", "id": 4107772383, "lat": -32.9856642, "lon": -52.9292769}, {"type": "node", "id": 4107772384, "lat": -32.9857816, "lon": -52.9293002}, {"type": "node", "id": 4107772385, "lat": -32.9858843, "lon": -52.9293002}, {"type": "node", "id": 4107772386, "lat": -32.9860016, "lon": -52.929271}, {"type": "node", "id": 4107772387, "lat": -32.9860799, "lon": -52.9292127}, {"type": "node", "id": 4107772388, "lat": -32.9863439, "lon": -52.9290495}, {"type": "node", "id": 4107772389, "lat": -32.9870188, "lon": -52.9286181}, {"type": "node", "id": 4107772390, "lat": -32.9876691, "lon": -52.9282625}, {"type": "node", "id": 4107772391, "lat": -32.9880701, "lon": -52.928041}, {"type": "node", "id": 4107772392, "lat": -32.988383, "lon": -52.9278661}, {"type": "node", "id": 4107772393, "lat": -32.9885591, "lon": -52.9278194}, {"type": "node", "id": 4107772394, "lat": -32.9887009, "lon": -52.9278194}, {"type": "node", "id": 4107772395, "lat": -32.9888329, "lon": -52.9278719}, {"type": "node", "id": 4107772396, "lat": -32.991713, "lon": -52.9287755}, {"type": "node", "id": 4107772397, "lat": -32.9920846, "lon": -52.9289329}, {"type": "node", "id": 4107772398, "lat": -32.9923339, "lon": -52.9290437}, {"type": "node", "id": 4107772399, "lat": -32.9924855, "lon": -52.9290612}, {"type": "node", "id": 4107772400, "lat": -32.9932434, "lon": -52.9293002}, {"type": "node", "id": 4107772401, "lat": -32.9941333, "lon": -52.9295917}, {"type": "node", "id": 4107772402, "lat": -32.9965145, "lon": -52.9302796}, {"type": "node", "id": 4107772403, "lat": -32.9989591, "lon": -52.9311016}, {"type": "node", "id": 4107772404, "lat": -32.9996974, "lon": -52.9313756}, {"type": "node", "id": 4107772405, "lat": -33.0013695, "lon": -52.9319294}, {"type": "node", "id": 4107772406, "lat": -33.0015602, "lon": -52.9319818}, {"type": "node", "id": 4107772407, "lat": -33.0018437, "lon": -52.9320751}, {"type": "node", "id": 4107772408, "lat": -33.0019904, "lon": -52.9321159}, {"type": "node", "id": 4107772409, "lat": -33.0021273, "lon": -52.9321742}, {"type": "node", "id": 4107772410, "lat": -33.0032371, "lon": -52.9325648}, {"type": "node", "id": 4107772411, "lat": -33.003594, "lon": -52.9326872}, {"type": "node", "id": 4107772412, "lat": -33.0037456, "lon": -52.9327455}, {"type": "node", "id": 4107772413, "lat": -33.004034, "lon": -52.9328097}, {"type": "node", "id": 4107772414, "lat": -33.009226, "lon": -52.93362}, {"type": "node", "id": 4107772415, "lat": -33.0114014, "lon": -52.9339523}, {"type": "node", "id": 4107772416, "lat": -33.0114747, "lon": -52.9339406}, {"type": "node", "id": 4107772417, "lat": -33.0115481, "lon": -52.9339115}, {"type": "node", "id": 4107772418, "lat": -33.0116067, "lon": -52.9338707}, {"type": "node", "id": 4107772419, "lat": -33.0116507, "lon": -52.9338299}, {"type": "node", "id": 4107772420, "lat": -33.0116898, "lon": -52.9337891}, {"type": "node", "id": 4107772421, "lat": -33.0117387, "lon": -52.933655}, {"type": "node", "id": 4107772422, "lat": -33.0120125, "lon": -52.9326406}, {"type": "node", "id": 4107772423, "lat": -33.0120809, "lon": -52.9323958}, {"type": "node", "id": 4107772424, "lat": -33.0121102, "lon": -52.9322442}, {"type": "node", "id": 4107772425, "lat": -33.0121396, "lon": -52.9321159}, {"type": "node", "id": 4107772426, "lat": -33.0121982, "lon": -52.9318886}, {"type": "node", "id": 4107772427, "lat": -33.0124133, "lon": -52.9311307}, {"type": "node", "id": 4107772428, "lat": -33.0128777, "lon": -52.9292361}, {"type": "node", "id": 4107772429, "lat": -33.0132395, "lon": -52.9279127}, {"type": "node", "id": 4107772430, "lat": -33.0138212, "lon": -52.9255692}, {"type": "node", "id": 4107772431, "lat": -33.0147353, "lon": -52.922048}, {"type": "node", "id": 4107772432, "lat": -33.0152682, "lon": -52.9199144}, {"type": "node", "id": 4107772433, "lat": -33.0159183, "lon": -52.9174251}, {"type": "node", "id": 4107772434, "lat": -33.0160943, "lon": -52.9166322}, {"type": "node", "id": 4107772435, "lat": -33.0161921, "lon": -52.916265}, {"type": "node", "id": 4107772436, "lat": -33.0163827, "lon": -52.9155654}, {"type": "node", "id": 4107772437, "lat": -33.0169498, "lon": -52.9133618}, {"type": "node", "id": 4107772438, "lat": -33.0170329, "lon": -52.9130295}, {"type": "node", "id": 4107772439, "lat": -33.0171355, "lon": -52.9126447}, {"type": "node", "id": 4107772440, "lat": -33.0171795, "lon": -52.9125573}, {"type": "node", "id": 4107772441, "lat": -33.0173213, "lon": -52.9123591}, {"type": "node", "id": 4107772442, "lat": -33.0183624, "lon": -52.9111115}, {"type": "node", "id": 4107772443, "lat": -33.0184944, "lon": -52.9109308}, {"type": "node", "id": 4107772444, "lat": -33.0186215, "lon": -52.9107967}, {"type": "node", "id": 4107772445, "lat": -33.0188219, "lon": -52.9105519}, {"type": "node", "id": 4107772446, "lat": -33.0189441, "lon": -52.9103886}, {"type": "node", "id": 4107772447, "lat": -33.019037, "lon": -52.910272}, {"type": "node", "id": 4107772448, "lat": -33.019125, "lon": -52.9100972}, {"type": "node", "id": 4107772449, "lat": -33.0192619, "lon": -52.9099048}, {"type": "node", "id": 4107772450, "lat": -33.0204252, "lon": -52.9081908}, {"type": "node", "id": 4107772451, "lat": -33.0211389, "lon": -52.9071823}, {"type": "node", "id": 4107772452, "lat": -33.0215055, "lon": -52.9067101}, {"type": "node", "id": 4107772453, "lat": -33.0216472, "lon": -52.9065002}, {"type": "node", "id": 4107772454, "lat": -33.0218037, "lon": -52.906133}, {"type": "node", "id": 4107772455, "lat": -33.0218868, "lon": -52.9059814}, {"type": "node", "id": 4107772456, "lat": -33.0220872, "lon": -52.9055558}, {"type": "node", "id": 4107772457, "lat": -33.023402, "lon": -52.902606}, {"type": "node", "id": 4107772458, "lat": -33.0243894, "lon": -52.9003907}, {"type": "node", "id": 4107772459, "lat": -33.0244871, "lon": -52.9001808}, {"type": "node", "id": 4107772460, "lat": -33.0245751, "lon": -52.9000817}, {"type": "node", "id": 4107772461, "lat": -33.0247755, "lon": -52.8999302}, {"type": "node", "id": 4107772462, "lat": -33.0259632, "lon": -52.8991956}, {"type": "node", "id": 4107772463, "lat": -33.0260219, "lon": -52.8991257}, {"type": "node", "id": 4107772464, "lat": -33.0260952, "lon": -52.8990207}, {"type": "node", "id": 4107772465, "lat": -33.0262125, "lon": -52.8987642}, {"type": "node", "id": 4107772466, "lat": -33.02654, "lon": -52.8979306}, {"type": "node", "id": 4107772467, "lat": -33.0274002, "lon": -52.8957678}, {"type": "node", "id": 4107772468, "lat": -33.0276495, "lon": -52.8951615}, {"type": "node", "id": 4107772469, "lat": -33.0278108, "lon": -52.8948059}, {"type": "node", "id": 4107772470, "lat": -33.0279476, "lon": -52.8944852}, {"type": "node", "id": 4107772471, "lat": -33.028148, "lon": -52.894083}, {"type": "node", "id": 4107772472, "lat": -33.0284657, "lon": -52.8933892}, {"type": "node", "id": 4107772473, "lat": -33.0287101, "lon": -52.892952}, {"type": "node", "id": 4107772474, "lat": -33.0289105, "lon": -52.8925964}, {"type": "node", "id": 4107772475, "lat": -33.0292966, "lon": -52.8919959}, {"type": "node", "id": 4107772476, "lat": -33.0298831, "lon": -52.8911681}, {"type": "node", "id": 4107772477, "lat": -33.0303768, "lon": -52.8904686}, {"type": "node", "id": 4107772478, "lat": -33.0304892, "lon": -52.8903112}, {"type": "node", "id": 4107772479, "lat": -33.0305674, "lon": -52.890247}, {"type": "node", "id": 4107772480, "lat": -33.0308313, "lon": -52.8900546}, {"type": "node", "id": 4107772481, "lat": -33.0345213, "lon": -52.887851}, {"type": "node", "id": 4107772482, "lat": -33.0365984, "lon": -52.8865335}, {"type": "node", "id": 4107772483, "lat": -33.0367157, "lon": -52.8864636}, {"type": "node", "id": 4107772484, "lat": -33.0368036, "lon": -52.8863936}, {"type": "node", "id": 4107772485, "lat": -33.036872, "lon": -52.8863411}, {"type": "node", "id": 4107772486, "lat": -33.03696, "lon": -52.8862712}, {"type": "node", "id": 4107772487, "lat": -33.037048, "lon": -52.8861604}, {"type": "node", "id": 4107772488, "lat": -33.037175, "lon": -52.8858922}, {"type": "node", "id": 4107772489, "lat": -33.0374292, "lon": -52.8853034}, {"type": "node", "id": 4107772490, "lat": -33.0390615, "lon": -52.8813917}, {"type": "node", "id": 4107772491, "lat": -33.0391397, "lon": -52.8812868}, {"type": "node", "id": 4107772492, "lat": -33.039213, "lon": -52.8812285}, {"type": "node", "id": 4107772493, "lat": -33.039428, "lon": -52.8811177}, {"type": "node", "id": 4107772494, "lat": -33.0404836, "lon": -52.8807446}, {"type": "node", "id": 4107772495, "lat": -33.0406106, "lon": -52.8807096}, {"type": "node", "id": 4107772496, "lat": -33.0407133, "lon": -52.8806397}, {"type": "node", "id": 4107772497, "lat": -33.0407866, "lon": -52.8805231}, {"type": "node", "id": 4107772498, "lat": -33.0410456, "lon": -52.8799226}, {"type": "node", "id": 4107772499, "lat": -33.0446814, "lon": -52.8713063}, {"type": "node", "id": 4107772500, "lat": -33.0457027, "lon": -52.8688287}, {"type": "node", "id": 4107772501, "lat": -33.0464647, "lon": -52.8670145}, {"type": "node", "id": 4107772502, "lat": -33.0009428, "lon": -52.9317881}, {"type": "node", "id": 4107772605, "lat": -33.0284741, "lon": -52.8515327}, {"type": "node", "id": 4107772606, "lat": -33.0205164, "lon": -52.8437925}, {"type": "node", "id": 4107772717, "lat": -32.9786015, "lon": -52.9116654}, {"type": "node", "id": 4121774104, "lat": -32.8399153, "lon": -53.0414713}, {"type": "node", "id": 4121774105, "lat": -32.8204143, "lon": -53.046168}, {"type": "node", "id": 4121774106, "lat": -32.8204449, "lon": -53.0461025}, {"type": "node", "id": 4121774107, "lat": -32.8210259, "lon": -53.0462335}, {"type": "node", "id": 4121774108, "lat": -32.8212032, "lon": -53.0463572}, {"type": "node", "id": 4121774109, "lat": -32.8220533, "lon": -53.047638}, {"type": "node", "id": 4121774110, "lat": -32.825319, "lon": -53.0525503}, {"type": "node", "id": 4121774111, "lat": -32.8254168, "lon": -53.0526813}, {"type": "node", "id": 4121774112, "lat": -32.8255514, "lon": -53.0528414}, {"type": "node", "id": 4121774113, "lat": -32.8256431, "lon": -53.052885}, {"type": "node", "id": 4121774114, "lat": -32.8258266, "lon": -53.0528195}, {"type": "node", "id": 4121774115, "lat": -32.825955, "lon": -53.0527322}, {"type": "node", "id": 4121774116, "lat": -32.8319111, "lon": -53.0479582}, {"type": "node", "id": 4121774117, "lat": -32.8359652, "lon": -53.0447198}, {"type": "node", "id": 4121774118, "lat": -32.8374939, "lon": -53.0434317}, {"type": "node", "id": 4121774119, "lat": -32.8396156, "lon": -53.0416487}, {"type": "node", "id": 4121774120, "lat": -32.8406856, "lon": -53.0443195}, {"type": "node", "id": 4121774121, "lat": -32.843113, "lon": -53.0538384}, {"type": "node", "id": 4121774122, "lat": -32.8432108, "lon": -53.0541731}, {"type": "node", "id": 4121774123, "lat": -32.8433209, "lon": -53.0543623}, {"type": "node", "id": 4121774124, "lat": -32.8434309, "lon": -53.0544351}, {"type": "node", "id": 4121774125, "lat": -32.8436571, "lon": -53.0545952}, {"type": "node", "id": 4121774126, "lat": -32.8444948, "lon": -53.0549227}, {"type": "node", "id": 4121774127, "lat": -32.8508837, "lon": -53.0572223}, {"type": "node", "id": 4121774128, "lat": -32.8589473, "lon": -53.0601187}, {"type": "node", "id": 4121774129, "lat": -32.8616798, "lon": -53.0612104}, {"type": "node", "id": 4121774130, "lat": -32.8620282, "lon": -53.0613413}, {"type": "node", "id": 4121774131, "lat": -32.8623094, "lon": -53.0614141}, {"type": "node", "id": 4121774132, "lat": -32.8626089, "lon": -53.0614723}, {"type": "node", "id": 4121774133, "lat": -32.864834, "lon": -53.0618508}, {"type": "node", "id": 4121774134, "lat": -32.8650968, "lon": -53.0618726}, {"type": "node", "id": 4121774135, "lat": -32.865164, "lon": -53.061858}, {"type": "node", "id": 4121774136, "lat": -32.8652374, "lon": -53.0618071}, {"type": "node", "id": 4121774137, "lat": -32.8653107, "lon": -53.061647}, {"type": "node", "id": 4121774138, "lat": -32.8656653, "lon": -53.060519}, {"type": "node", "id": 4121774139, "lat": -32.8666005, "lon": -53.0576954}, {"type": "node", "id": 4121774140, "lat": -32.8666494, "lon": -53.0576153}, {"type": "node", "id": 4121774141, "lat": -32.8667044, "lon": -53.0575644}, {"type": "node", "id": 4121774142, "lat": -32.8667839, "lon": -53.0575134}, {"type": "node", "id": 4121774143, "lat": -32.8668511, "lon": -53.0574989}, {"type": "node", "id": 4121774144, "lat": -32.8669367, "lon": -53.0574771}, {"type": "node", "id": 4121774145, "lat": -32.867224, "lon": -53.0575935}, {"type": "node", "id": 4121774146, "lat": -32.8754816, "lon": -53.0608028}, {"type": "node", "id": 4335884005, "lat": -32.8810183, "lon": -52.7191085}, {"type": "node", "id": 4335884006, "lat": -32.8810948, "lon": -52.7188478}, {"type": "node", "id": 4335884014, "lat": -32.9580564, "lon": -52.723576}, {"type": "node", "id": 4409113655, "lat": -33.1799939, "lon": -53.0087497}, {"type": "node", "id": 4409113664, "lat": -33.0671701, "lon": -52.8849328}, {"type": "node", "id": 4409117722, "lat": -32.5206779, "lon": -53.2161803}, {"type": "node", "id": 4409117723, "lat": -32.5211483, "lon": -53.2158369}, {"type": "node", "id": 4409117724, "lat": -32.5214016, "lon": -53.215558}, {"type": "node", "id": 4409117725, "lat": -32.523627, "lon": -53.2125539}, {"type": "node", "id": 4409117726, "lat": -32.523826, "lon": -53.2121891}, {"type": "node", "id": 4409117727, "lat": -32.5294707, "lon": -53.1974692}, {"type": "node", "id": 4409117728, "lat": -32.5294707, "lon": -53.1971473}, {"type": "node", "id": 4409117729, "lat": -32.529344, "lon": -53.1965036}, {"type": "node", "id": 4409117730, "lat": -32.5293802, "lon": -53.1961817}, {"type": "node", "id": 4409117731, "lat": -32.5296154, "lon": -53.1955165}, {"type": "node", "id": 4409117732, "lat": -32.5319853, "lon": -53.1894655}, {"type": "node", "id": 4409117733, "lat": -32.5321301, "lon": -53.1888003}, {"type": "node", "id": 4409117734, "lat": -32.5337401, "lon": -53.172707}, {"type": "node", "id": 4409117735, "lat": -32.5338306, "lon": -53.1723208}, {"type": "node", "id": 4409117736, "lat": -32.5339029, "lon": -53.1719345}, {"type": "node", "id": 4409117737, "lat": -32.5339029, "lon": -53.17172}, {"type": "node", "id": 4409117738, "lat": -32.5336497, "lon": -53.1707758}, {"type": "node", "id": 4409117739, "lat": -32.5335773, "lon": -53.1702608}, {"type": "node", "id": 4409117740, "lat": -32.5335592, "lon": -53.1680292}, {"type": "node", "id": 4409117741, "lat": -32.5336316, "lon": -53.1676645}, {"type": "node", "id": 4409117742, "lat": -32.5369421, "lon": -53.1583304}, {"type": "node", "id": 4409117743, "lat": -32.5372134, "lon": -53.1577939}, {"type": "node", "id": 4409117744, "lat": -32.5382626, "lon": -53.156485}, {"type": "node", "id": 4409117745, "lat": -32.5384073, "lon": -53.1561417}, {"type": "node", "id": 4409117746, "lat": -32.5408855, "lon": -53.1417221}, {"type": "node", "id": 4409117747, "lat": -32.5408675, "lon": -53.1413574}, {"type": "node", "id": 4409117748, "lat": -32.540777, "lon": -53.1410355}, {"type": "node", "id": 4409117749, "lat": -32.5392213, "lon": -53.138482}, {"type": "node", "id": 4409117750, "lat": -32.5392213, "lon": -53.1382674}, {"type": "node", "id": 4409117751, "lat": -32.5392756, "lon": -53.1380314}, {"type": "node", "id": 4409117752, "lat": -32.5472165, "lon": -53.1224746}, {"type": "node", "id": 4409117753, "lat": -32.5543247, "lon": -53.1085486}, {"type": "node", "id": 4409117754, "lat": -32.5545055, "lon": -53.1083984}, {"type": "node", "id": 4409117755, "lat": -32.554596, "lon": -53.1082267}, {"type": "node", "id": 4409117756, "lat": -32.5545417, "lon": -53.1079263}, {"type": "node", "id": 4409117757, "lat": -32.5534565, "lon": -53.1059307}, {"type": "node", "id": 4409117758, "lat": -32.5534565, "lon": -53.1056518}, {"type": "node", "id": 4409117759, "lat": -32.5538182, "lon": -53.1040854}, {"type": "node", "id": 4409117760, "lat": -32.5539991, "lon": -53.1038493}, {"type": "node", "id": 4409117761, "lat": -32.5542523, "lon": -53.1035918}, {"type": "node", "id": 4409117762, "lat": -32.5543066, "lon": -53.1033558}, {"type": "node", "id": 4409117763, "lat": -32.5543066, "lon": -53.103034}, {"type": "node", "id": 4409117764, "lat": -32.5541619, "lon": -53.1021971}, {"type": "node", "id": 4409117765, "lat": -32.5541981, "lon": -53.1018538}, {"type": "node", "id": 4409117766, "lat": -32.5543789, "lon": -53.1017036}, {"type": "node", "id": 4409117767, "lat": -32.5546321, "lon": -53.101725}, {"type": "node", "id": 4409117768, "lat": -32.5550662, "lon": -53.1020684}, {"type": "node", "id": 4409117769, "lat": -32.555229, "lon": -53.1021113}, {"type": "node", "id": 4409117770, "lat": -32.5555545, "lon": -53.1020469}, {"type": "node", "id": 4409117771, "lat": -32.5826433, "lon": -53.0829281}, {"type": "node", "id": 4409117772, "lat": -32.5973958, "lon": -53.0724353}, {"type": "node", "id": 4409117951, "lat": -32.5138403, "lon": -53.0622952}, {"type": "node", "id": 4409117952, "lat": -32.5137085, "lon": -53.0623696}, {"type": "node", "id": 4409117953, "lat": -32.5089948, "lon": -53.0672547}, {"type": "node", "id": 4726127022, "lat": -32.7486042, "lon": -52.647092}, {"type": "node", "id": 5152603346, "lat": -33.0545816, "lon": -53.2008192}, {"type": "node", "id": 5375470154, "lat": -32.8835766, "lon": -52.7202107}, {"type": "node", "id": 5433855936, "lat": -32.5497474, "lon": -53.23009}, {"type": "node", "id": 5433855937, "lat": -32.5500626, "lon": -53.228537}, {"type": "node", "id": 5433855938, "lat": -32.5509947, "lon": -53.2255692}, {"type": "node", "id": 5433855939, "lat": -32.5517966, "lon": -53.2241625}, {"type": "node", "id": 5433855940, "lat": -32.5520404, "lon": -53.2225464}, {"type": "node", "id": 5433855941, "lat": -32.5519873, "lon": -53.2214856}, {"type": "node", "id": 5433855942, "lat": -32.5526373, "lon": -53.2179062}, {"type": "node", "id": 5433855943, "lat": -32.5525672, "lon": -53.2124211}, {"type": "node", "id": 5433855944, "lat": -32.552496, "lon": -53.2065336}, {"type": "node", "id": 5433855945, "lat": -32.5547215, "lon": -53.2041318}, {"type": "node", "id": 5433855946, "lat": -32.5551162, "lon": -53.2031205}, {"type": "node", "id": 5433855947, "lat": -32.5551535, "lon": -53.2023467}, {"type": "node", "id": 5433855948, "lat": -32.5548574, "lon": -53.2020731}, {"type": "node", "id": 5433855949, "lat": -32.5512875, "lon": -53.1999421}, {"type": "node", "id": 5433855950, "lat": -32.5513039, "lon": -53.1992789}, {"type": "node", "id": 5433855951, "lat": -32.5520088, "lon": -53.1958451}, {"type": "node", "id": 5433855952, "lat": -32.5533675, "lon": -53.189043}, {"type": "node", "id": 5433855953, "lat": -32.5512208, "lon": -53.1812431}, {"type": "node", "id": 5433855954, "lat": -32.5513282, "lon": -53.1805846}, {"type": "node", "id": 5433855955, "lat": -32.5518846, "lon": -53.1746533}, {"type": "node", "id": 5433855984, "lat": -32.5306392, "lon": -53.1656232}, {"type": "node", "id": 5844664647, "lat": -33.1264424, "lon": -52.9456299}, {"type": "node", "id": 5844664660, "lat": -33.1355214, "lon": -52.9567079}, {"type": "node", "id": 5844691212, "lat": -32.9277697, "lon": -52.7682352}, {"type": "node", "id": 5844691213, "lat": -32.9281434, "lon": -52.7678919}, {"type": "node", "id": 5844691214, "lat": -32.9282875, "lon": -52.7678114}, {"type": "node", "id": 5844691215, "lat": -32.929904, "lon": -52.7672643}, {"type": "node", "id": 5844691216, "lat": -32.9313223, "lon": -52.7668405}, {"type": "node", "id": 5844691217, "lat": -32.9314483, "lon": -52.7667385}, {"type": "node", "id": 5844691218, "lat": -32.9324794, "lon": -52.7656871}, {"type": "node", "id": 5844691219, "lat": -32.9350142, "lon": -52.7636969}, {"type": "node", "id": 5844691220, "lat": -32.9351313, "lon": -52.7635896}, {"type": "node", "id": 5844691221, "lat": -32.9352033, "lon": -52.7634877}, {"type": "node", "id": 5844691222, "lat": -32.9354734, "lon": -52.7629137}, {"type": "node", "id": 5844691223, "lat": -32.9355857, "lon": -52.7625923}, {"type": "node", "id": 5844698754, "lat": -32.7858457, "lon": -52.6664553}, {"type": "node", "id": 6188074937, "lat": -33.0911823, "lon": -52.9069049}, {"type": "node", "id": 6215976092, "lat": -33.0372278, "lon": -52.8592944}, {"type": "node", "id": 6215978493, "lat": -33.0345742, "lon": -52.8570767}, {"type": "node", "id": 6215990040, "lat": -32.9961565, "lon": -52.8200035}, {"type": "node", "id": 6216004446, "lat": -33.0335936, "lon": -52.8562572}, {"type": "node", "id": 6216048173, "lat": -33.0338281, "lon": -52.8564532}, {"type": "node", "id": 6216048389, "lat": -33.0396637, "lon": -52.8613302}, {"type": "node", "id": 6900757928, "lat": -33.1145831, "lon": -52.9284924}, {"type": "node", "id": 6900757929, "lat": -32.9418681, "lon": -52.7713752}, {"type": "node", "id": 6900757930, "lat": -32.9427885, "lon": -52.7697388}, {"type": "node", "id": 6900757931, "lat": -32.9425617, "lon": -52.7724539}, {"type": "node", "id": 6900757932, "lat": -32.9434207, "lon": -52.7702402}, {"type": "node", "id": 6900757933, "lat": -32.9435189, "lon": -52.7702218}, {"type": "node", "id": 6900757934, "lat": -32.9437026, "lon": -52.7700818}, {"type": "node", "id": 6900757935, "lat": -32.9426683, "lon": -52.7696321}, {"type": "node", "id": 6900757936, "lat": -32.9428383, "lon": -52.7693171}, {"type": "node", "id": 6900757937, "lat": -32.9414637, "lon": -52.7685634}, {"type": "node", "id": 6900757938, "lat": -32.9416463, "lon": -52.7682624}, {"type": "node", "id": 6900757939, "lat": -32.9401039, "lon": -52.7673569}, {"type": "node", "id": 6900757940, "lat": -32.9402837, "lon": -52.7670567}, {"type": "node", "id": 6900757945, "lat": -32.9384033, "lon": -52.7654267}, {"type": "node", "id": 6900757946, "lat": -32.9334807, "lon": -52.7572498}, {"type": "node", "id": 6900757947, "lat": -32.9072393, "lon": -52.7333473}, {"type": "node", "id": 6900757948, "lat": -32.6861284, "lon": -52.6123534}, {"type": "node", "id": 7249975047, "lat": -32.8559597, "lon": -52.7050467}, {"type": "node", "id": 7249975048, "lat": -32.8550653, "lon": -52.7045556}, {"type": "node", "id": 7249975049, "lat": -32.8510376, "lon": -52.7023445}, {"type": "node", "id": 7249975050, "lat": -32.8501672, "lon": -52.7018667}, {"type": "node", "id": 7249975051, "lat": -32.8861262, "lon": -52.7216109}, {"type": "node", "id": 7249975052, "lat": -32.8869591, "lon": -52.7220683}, {"type": "node", "id": 7249975053, "lat": -32.8820229, "lon": -52.7193575}, {"type": "node", "id": 7250036154, "lat": -33.2022182, "lon": -53.0340931}, {"type": "node", "id": 8003574299, "lat": -33.082956, "lon": -52.8993768}, {"type": "node", "id": 8003700639, "lat": -33.098013, "lon": -52.9131563}, {"type": "node", "id": 8003720993, "lat": -33.1158577, "lon": -52.9301337}, {"type": "node", "id": 8499358811, "lat": -32.9357638, "lon": -53.1523383}, {"type": "node", "id": 8499358812, "lat": -32.9363379, "lon": -53.1459975}, {"type": "node", "id": 8499358813, "lat": -32.936142, "lon": -53.1478322}, {"type": "node", "id": 8499358814, "lat": -32.9372698, "lon": -53.1482506}, {"type": "node", "id": 8499358815, "lat": -32.9341903, "lon": -53.1562959}, {"type": "node", "id": 8499358816, "lat": -32.9373295, "lon": -53.1483699}, {"type": "node", "id": 8499399417, "lat": -32.9362219, "lon": -53.1478737}, {"type": "node", "id": 8499399418, "lat": -32.9360812, "lon": -53.1477517}, {"type": "node", "id": 8499399419, "lat": -32.9360655, "lon": -53.1475988}, {"type": "node", "id": 8499399420, "lat": -32.9363176, "lon": -53.146078}, {"type": "node", "id": 8499399421, "lat": -32.9390572, "lon": -53.1328064}, {"type": "node", "id": 8499399422, "lat": -32.9406033, "lon": -53.1279237}, {"type": "node", "id": 8499399423, "lat": -32.9429109, "lon": -53.1249087}, {"type": "node", "id": 8499399424, "lat": -32.9420398, "lon": -53.1286356}, {"type": "node", "id": 8499399425, "lat": -32.943737, "lon": -53.1293759}, {"type": "node", "id": 8499399426, "lat": -32.9491661, "lon": -53.1321385}, {"type": "node", "id": 8499399427, "lat": -32.9405248, "lon": -53.1278785}, {"type": "node", "id": 8499399428, "lat": -32.9408242, "lon": -53.1268747}, {"type": "node", "id": 8499399429, "lat": -32.9412142, "lon": -53.1258776}, {"type": "node", "id": 8499399430, "lat": -32.9412727, "lon": -53.1258012}, {"type": "node", "id": 8499399431, "lat": -32.9416003, "lon": -53.1256047}, {"type": "node", "id": 8499399432, "lat": -32.9421439, "lon": -53.1252996}, {"type": "node", "id": 8499399433, "lat": -32.9423712, "lon": -53.1252084}, {"type": "node", "id": 8499399434, "lat": -32.9426076, "lon": -53.1251373}, {"type": "node", "id": 8499399435, "lat": -32.9427769, "lon": -53.1250374}, {"type": "node", "id": 8499399436, "lat": -32.9430268, "lon": -53.124623}, {"type": "node", "id": 8499399437, "lat": -32.9435929, "lon": -53.1231867}, {"type": "node", "id": 8499399438, "lat": -32.9459552, "lon": -53.1173234}, {"type": "node", "id": 8499399439, "lat": -32.9469085, "lon": -53.1148115}, {"type": "node", "id": 8499399440, "lat": -32.9469659, "lon": -53.1147297}, {"type": "node", "id": 8499399441, "lat": -32.947048, "lon": -53.1147015}, {"type": "node", "id": 8499399442, "lat": -32.9473271, "lon": -53.1146546}, {"type": "node", "id": 8499399443, "lat": -32.9483434, "lon": -53.1141087}, {"type": "node", "id": 8499399444, "lat": -32.9484874, "lon": -53.11398}, {"type": "node", "id": 8499399445, "lat": -32.9485572, "lon": -53.1138217}, {"type": "node", "id": 8499399446, "lat": -32.9486613, "lon": -53.1137185}, {"type": "node", "id": 8499399447, "lat": -32.9488284, "lon": -53.113634}, {"type": "node", "id": 8499399448, "lat": -32.9490124, "lon": -53.1136179}, {"type": "node", "id": 8499399449, "lat": -32.9493405, "lon": -53.1136715}, {"type": "node", "id": 8499399450, "lat": -32.9498002, "lon": -53.113758}, {"type": "node", "id": 8499399451, "lat": -32.9498666, "lon": -53.1137487}, {"type": "node", "id": 8499399452, "lat": -32.9499223, "lon": -53.1137131}, {"type": "node", "id": 8499399453, "lat": -32.9499696, "lon": -53.1136099}, {"type": "node", "id": 8499399454, "lat": -32.9502498, "lon": -53.1126972}, {"type": "node", "id": 8499399455, "lat": -32.9508383, "lon": -53.1108445}, {"type": "node", "id": 8499399456, "lat": -32.9518692, "lon": -53.1075856}, {"type": "node", "id": 8499399457, "lat": -32.952963, "lon": -53.1040585}, {"type": "node", "id": 8499399458, "lat": -32.9534525, "lon": -53.10259}, {"type": "node", "id": 8499399459, "lat": -32.9595123, "lon": -53.1394529}, {"type": "node", "id": 8499399460, "lat": -32.9518152, "lon": -53.133713}, {"type": "node", "id": 8499399461, "lat": -32.9524791, "lon": -53.1343219}, {"type": "node", "id": 8502579272, "lat": -32.9463255, "lon": -53.1393725}, {"type": "node", "id": 8502579273, "lat": -32.9433971, "lon": -53.1468371}, {"type": "node", "id": 8502579274, "lat": -32.9441534, "lon": -53.1472528}, {"type": "node", "id": 8502579275, "lat": -32.9434669, "lon": -53.1469202}, {"type": "node", "id": 8502579276, "lat": -32.9434376, "lon": -53.14666}, {"type": "node", "id": 8502579277, "lat": -32.9510454, "lon": -53.1214446}, {"type": "node", "id": 8502579278, "lat": -32.9523036, "lon": -53.1182796}, {"type": "node", "id": 8502579280, "lat": -32.9524206, "lon": -53.1181642}, {"type": "node", "id": 8502579281, "lat": -32.9528348, "lon": -53.1181857}, {"type": "node", "id": 8502579282, "lat": -32.952945, "lon": -53.1180784}, {"type": "node", "id": 8502579284, "lat": -32.9542684, "lon": -53.1130868}, {"type": "node", "id": 8502579285, "lat": -32.9566653, "lon": -53.1045064}, {"type": "node", "id": 8502639445, "lat": -32.9557088, "lon": -53.1369612}, {"type": "node", "id": 8502639446, "lat": -32.9525196, "lon": -53.1513365}, {"type": "node", "id": 8502639447, "lat": -32.9499966, "lon": -53.1531617}, {"type": "node", "id": 8502639448, "lat": -32.9500821, "lon": -53.1519279}, {"type": "node", "id": 8502639449, "lat": -32.9501609, "lon": -53.151775}, {"type": "node", "id": 8502639450, "lat": -32.9524262, "lon": -53.1514062}, {"type": "node", "id": 8502639451, "lat": -32.9525872, "lon": -53.1512265}, {"type": "node", "id": 8502639452, "lat": -32.9526558, "lon": -53.1510119}, {"type": "node", "id": 8502639453, "lat": -32.953636, "lon": -53.1485698}, {"type": "node", "id": 8502639454, "lat": -32.9555513, "lon": -53.1437472}, {"type": "node", "id": 8502639455, "lat": -32.9568026, "lon": -53.1405473}, {"type": "node", "id": 8502639456, "lat": -32.9577068, "lon": -53.1382704}, {"type": "node", "id": 8508849361, "lat": -33.0361498, "lon": -53.1877273}, {"type": "node", "id": 8508849362, "lat": -33.0252908, "lon": -53.1803405}, {"type": "node", "id": 8508849363, "lat": -33.0133014, "lon": -53.1733319}, {"type": "node", "id": 8508849364, "lat": -33.0338832, "lon": -53.184498}, {"type": "node", "id": 8508849365, "lat": -33.0322214, "lon": -53.1820491}, {"type": "node", "id": 8508849366, "lat": -33.0319044, "lon": -53.1819499}, {"type": "node", "id": 8508849367, "lat": -32.9820056, "lon": -53.158679}, {"type": "node", "id": 8508849368, "lat": -32.9812271, "lon": -53.1580567}, {"type": "node", "id": 8508849369, "lat": -32.9748415, "lon": -53.1523114}, {"type": "node", "id": 8508849370, "lat": -32.9735319, "lon": -53.1508255}, {"type": "node", "id": 8508849371, "lat": -32.9798096, "lon": -53.1567586}, {"type": "node", "id": 8508849372, "lat": -33.0415372, "lon": -53.1946689}, {"type": "node", "id": 8508849373, "lat": -33.0463262, "lon": -53.1967825}, {"type": "node", "id": 8508849374, "lat": -33.0481743, "lon": -53.1976569}, {"type": "node", "id": 8508849375, "lat": -33.0430571, "lon": -53.1955326}, {"type": "node", "id": 8510215378, "lat": -32.9337986, "lon": -53.1247035}, {"type": "node", "id": 8510215379, "lat": -32.9380397, "lon": -53.1267607}, {"type": "node", "id": 8510215380, "lat": -32.9296068, "lon": -53.1227227}, {"type": "node", "id": 8510215381, "lat": -32.8911127, "lon": -53.1023137}, {"type": "node", "id": 8510215382, "lat": -32.8905767, "lon": -53.1017129}, {"type": "node", "id": 8510215383, "lat": -32.8893368, "lon": -53.1001666}, {"type": "node", "id": 8510215384, "lat": -32.9060935, "lon": -53.1115244}, {"type": "node", "id": 8510215385, "lat": -32.9056285, "lon": -53.1110738}, {"type": "node", "id": 8510215386, "lat": -32.9023643, "lon": -53.1080188}, {"type": "node", "id": 8530734038, "lat": -32.549033, "lon": -53.2339956}, {"type": "node", "id": 8530734039, "lat": -32.5517363, "lon": -53.1759511}, {"type": "node", "id": 8530734040, "lat": -32.5512163, "lon": -53.1809963}, {"type": "node", "id": 8530734041, "lat": -32.5533822, "lon": -53.1892642}, {"type": "node", "id": 8530734042, "lat": -32.5528735, "lon": -53.1917936}, {"type": "node", "id": 8530734043, "lat": -32.5528984, "lon": -53.1913054}, {"type": "node", "id": 8530734044, "lat": -32.551222, "lon": -53.1996752}, {"type": "node", "id": 8530734045, "lat": -32.5512299, "lon": -53.1998147}, {"type": "node", "id": 8530734046, "lat": -32.5543611, "lon": -53.2017848}, {"type": "node", "id": 8530734047, "lat": -32.5548732, "lon": -53.2038876}, {"type": "node", "id": 8530734048, "lat": -32.5525344, "lon": -53.2063526}, {"type": "node", "id": 8530734049, "lat": -32.5526282, "lon": -53.2062493}, {"type": "node", "id": 8530734050, "lat": -32.5525796, "lon": -53.2183447}, {"type": "node", "id": 8530734051, "lat": -32.5522066, "lon": -53.2202049}, {"type": "node", "id": 8530734052, "lat": -32.5520257, "lon": -53.2223654}, {"type": "node", "id": 8530734053, "lat": -32.5519816, "lon": -53.2222554}, {"type": "node", "id": 8530734054, "lat": -32.5519737, "lon": -53.2228951}, {"type": "node", "id": 8530734055, "lat": -32.5517533, "lon": -53.2242697}, {"type": "node", "id": 8530734056, "lat": -32.5511089, "lon": -53.2253064}, {"type": "node", "id": 8530734057, "lat": -32.55, "lon": -53.2287678}, {"type": "node", "id": 8536516932, "lat": -32.9988809, "lon": -53.0967978}, {"type": "node", "id": 8536516933, "lat": -32.995943, "lon": -53.0973959}, {"type": "node", "id": 8536516934, "lat": -32.9870904, "lon": -53.1000835}, {"type": "node", "id": 8536516935, "lat": -32.9879183, "lon": -53.0997777}, {"type": "node", "id": 8536516936, "lat": -32.9912074, "lon": -53.098796}, {"type": "node", "id": 8536516937, "lat": -32.9798682, "lon": -53.1022239}, {"type": "node", "id": 8536516938, "lat": -32.9840711, "lon": -53.1009901}, {"type": "node", "id": 8536516939, "lat": -32.9606645, "lon": -53.1050992}, {"type": "node", "id": 8536516940, "lat": -32.9588709, "lon": -53.105287}, {"type": "node", "id": 8536726538, "lat": -33.0039388, "lon": -53.0961058}, {"type": "node", "id": 8755437149, "lat": -33.1996032, "lon": -53.031683}, {"type": "node", "id": 8755437151, "lat": -33.1827369, "lon": -53.0119627}, {"type": "node", "id": 8755437153, "lat": -33.1869929, "lon": -53.016948}, {"type": "node", "id": 8755437155, "lat": -33.1913358, "lon": -53.0220353}, {"type": "node", "id": 8755437156, "lat": -33.192833, "lon": -53.0237893}, {"type": "node", "id": 8755437157, "lat": -33.1956926, "lon": -53.0271393}, {"type": "node", "id": 8755437160, "lat": -33.1725742, "lon": -53.0000536}, {"type": "node", "id": 8819989302, "lat": -33.1171419, "lon": -52.931968}, {"type": "node", "id": 8897871977, "lat": -32.9373216, "lon": -53.1482881}, {"type": "node", "id": 8897871978, "lat": -32.9484289, "lon": -53.1140538}, {"type": "node", "id": 8897871979, "lat": -32.9131338, "lon": -53.1148611}, {"type": "node", "id": 8897871980, "lat": -32.8985629, "lon": -53.1042811}, {"type": "node", "id": 8897871981, "lat": -32.8917569, "lon": -53.1026879}, {"type": "node", "id": 8897871982, "lat": -32.94284, "lon": -53.0920811}, {"type": "node", "id": 8897871983, "lat": -32.9414883, "lon": -53.08752}, {"type": "node", "id": 8897871984, "lat": -32.9363896, "lon": -53.0821851}, {"type": "node", "id": 8897871985, "lat": -32.9256872, "lon": -53.06831}, {"type": "node", "id": 8897871986, "lat": -32.9205404, "lon": -53.067335}, {"type": "node", "id": 8897871987, "lat": -32.8874618, "lon": -53.0652443}, {"type": "node", "id": 8897871988, "lat": -32.9148169, "lon": -53.0663815}, {"type": "node", "id": 8897871989, "lat": -32.9169942, "lon": -53.0667409}, {"type": "node", "id": 8897871990, "lat": -32.9179219, "lon": -53.0667812}, {"type": "node", "id": 8897871991, "lat": -32.9226534, "lon": -53.0676958}, {"type": "node", "id": 8897871992, "lat": -32.9073298, "lon": -53.0643109}, {"type": "node", "id": 8897871993, "lat": -32.9017709, "lon": -53.0625299}, {"type": "node", "id": 8897871994, "lat": -32.8892433, "lon": -53.0585159}, {"type": "node", "id": 8900892746, "lat": -32.9405209, "lon": -53.1276948}, {"type": "node", "id": 8900892747, "lat": -32.9461443, "lon": -53.116736}, {"type": "node", "id": 8900892748, "lat": -32.9405248, "lon": -53.1276204}, {"type": "node", "id": 12855594728, "lat": -33.1298391, "lon": -52.9500638}, {"type": "node", "id": 12855594736, "lat": -33.130144, "lon": -52.9504186}, {"type": "way", "id": 298641627, "nodes": [321260516, 2665850615, 6900757940, 6900757938, 6900757936, 3372689554, 6900757934, 3372689552, 321260517, 3372689561, 3372689574, 3372676363, 6215990040, 4107772059, 4107772606, 321260518, 4107772605, 321260519, 6216004446, 6216048173, 6215978493, 6215976092, 6216048389, 4107772501, 3372701342, 3459365240, 321260520, 4409113664, 8003574299, 6188074937, 8003700639, 3372701333, 3372689645, 321260521, 321260536, 6900757928, 321260539, 8003720993, 8819989302, 5844664647, 321260541, 321260543, 3372701295, 12855594728, 12855594736, 5844664660, 3373306688, 3372673806, 3372700359, 3372700358, 3372700362, 8755437160, 3372673786, 4409113655, 8755437151, 8755437153, 8755437155, 8755437156, 8755437157, 321260544, 8755437149, 321260545, 321260546, 7250036154], "tags": {"highway": "trunk", "lanes": "2", "maxspeed": "110", "maxspeed:bus": "80", "maxspeed:hgv": "80", "name": "Rodovia Brigadeiro Jos\u00e9 da Silva Paes", "oneway": "no", "ref": "BR-471", "surface": "asphalt"}}, {"type": "way", "id": 330306309, "nodes": [3372689514, 3372689513, 3372689512, 3372689511, 3372689507, 3372689506, 3372689505, 3372689504, 3372689503, 3372689502, 3372689501, 4335884014, 3372689500, 3372689499, 3372689498, 3372689497, 3372689496, 3372689495, 3372689494, 3372689493, 3372676348, 3372676349, 3372676350, 3372676351, 3372676352, 3372676353, 3372676354, 3372676355, 3372676356, 3372676357, 3372676358, 3372676359, 3372676360, 3372676361, 3372676362, 3372676363], "tags": {"highway": "unclassified", "surface": "unpaved"}}, {"type": "way", "id": 330307680, "nodes": [6900757934, 6900757933, 6900757932, 3372689515, 6900757930, 6900757935, 6900757937, 6900757939, 3372689516], "tags": {"highway": "residential"}}, {"type": "way", "id": 330307681, "nodes": [321260516, 3372689516, 3372689517, 3372689518, 3372689519, 6900757929, 3372689520, 6900757931, 3372689521], "tags": {"highway": "unclassified"}}, {"type": "way", "id": 330307685, "nodes": [3372689541, 3372689542, 3372689543, 3372689544, 6900757946, 3372689545, 3372689546, 3372689547, 3372689548, 3372689549, 3372689550, 3372689551], "tags": {"highway": "unclassified"}}, {"type": "way", "id": 330307686, "nodes": [3372689552, 3372689553, 4092595713, 3372689496], "tags": {"highway": "unclassified"}}, {"type": "way", "id": 330308278, "nodes": [3372692664, 3372692665, 3372692666], "tags": {"highway": "residential"}}, {"type": "way", "id": 330308279, "nodes": [3372692668, 3372692666, 3372692667, 4085213005, 4085213006, 4085213007, 4085213008, 4085213009, 4335884005, 4085213010], "tags": {"highway": "unclassified"}}, {"type": "way", "id": 330308280, "nodes": [3372692666, 4085213003, 3372692669, 3372692670, 3372692671, 3372692672, 3372692673, 2665850614], "tags": {"highway": "unclassified"}}, {"type": "way", "id": 330308281, "nodes": [3372692674, 3372692675, 3372692676, 3372692677, 3372692678, 3372692679, 3372692680], "tags": {"highway": "unclassified"}}, {"type": "way", "id": 330308291, "nodes": [3372695653, 3372695658, 3372695659, 3372695660, 3372695661, 3372695662], "tags": {"highway": "unclassified"}}, {"type": "way", "id": 330367320, "nodes": [3373306328, 3373306329, 3373306330, 3373306331, 3373306332, 3373306333, 3373306334, 3373306335, 3373306336, 3373306337, 3373306338, 3373306339, 3373306340, 3373306341, 3373306342, 3373306343, 3373306344, 3373306345, 3373306346, 3373306347, 3373306348, 3373306349, 3373306350, 3373306351, 3373306352, 3373306353, 3373306354, 3373306355, 3373306356], "tags": {"highway": "unclassified", "seasonal": "yes", "surface": "unpaved", "tracktype": "grade5"}}, {"type": "way", "id": 330367327, "nodes": [3373306367, 3373306368, 3373306356, 8897871987, 3373306369, 3373306370, 8897871994, 3373306371, 3373306372, 8897871993, 8897871992, 3373306379, 8897871988, 8897871989, 8897871990, 8897871986, 8897871991, 3373306380, 8897871985, 3373306381, 3373306382, 3373306383, 8897871984, 3373306384, 8897871983, 3373306385, 8897871982, 3373306386, 3373306387, 8499399458, 3373306388, 8502579285, 3373306389, 8536516940, 8536516939, 3373306390, 3373306391, 8536516937, 8536516938, 8536516934, 8536516935, 8536516936, 3373306392, 8536516933, 3373306593, 8536516932, 3373306594, 8536726538], "tags": {"highway": "unclassified", "surface": "unpaved"}}, {"type": "way", "id": 346967691, "nodes": [3534112857, 3534112858, 3534112859, 3534112860, 3534112861], "tags": {"highway": "unclassified"}}, {"type": "way", "id": 346967694, "nodes": [3534112864, 3534112865, 3534112866, 3534112867], "tags": {"highway": "unclassified"}}, {"type": "way", "id": 405547560, "nodes": [4077294577, 4077294578, 4077294579, 4077294580, 4077294581, 4077294582, 4077294583, 4077294584], "tags": {"highway": "unclassified"}}, {"type": "way", "id": 406454791, "nodes": [4085213002, 4085213003, 4085213004], "tags": {"highway": "unclassified", "surface": "unpaved"}}, {"type": "way", "id": 408866846, "nodes": [4107772059, 4107772060, 4107772061, 4107772062, 4107772063, 4107772064, 4107772065, 4107772066, 4107772067, 4107772068, 4107772069, 4107772070, 4107772071, 4107772072, 4107772073, 4107772074, 4107772075, 4107772076, 4107772077, 4107772078, 4107772079, 4107772080, 4107772081, 4107772082, 4107772083, 4107772084, 4107772085, 4107772086, 4107772087, 4107772717, 4107772088, 4107772289, 4107772290, 4107772291, 4107772292, 4107772293], "tags": {"highway": "unclassified", "surface": "unpaved"}}, {"type": "way", "id": 408866851, "nodes": [4107772293, 4107772357, 4107772358, 4107772359, 4107772360, 4107772361, 4107772362, 4107772363, 4107772364, 4107772365, 4107772366, 4107772367, 4107772368, 4107772369, 4107772370, 4107772371, 4107772372, 4107772373, 4107772374, 4107772375, 4107772376, 4107772377, 4107772378, 4107772379, 4107772380, 4107772381, 4107772382, 4107772383, 4107772384, 4107772385, 4107772386, 4107772387, 4107772388, 4107772389, 4107772390, 4107772391, 4107772392, 4107772393, 4107772394, 4107772395, 4107772396, 4107772397, 4107772398, 4107772399, 4107772400, 4107772401, 4107772402, 4107772403, 4107772404, 4107772502, 4107772405, 4107772406, 4107772407, 4107772408, 4107772409, 4107772410, 4107772411, 4107772412, 4107772413, 4107772414, 4107772415, 4107772416, 4107772417, 4107772418, 4107772419, 4107772420, 4107772421, 4107772422, 4107772423, 4107772424, 4107772425, 4107772426, 4107772427, 4107772428, 4107772429, 4107772430, 4107772431, 4107772432, 4107772433, 4107772434, 4107772435, 4107772436, 4107772437, 4107772438, 4107772439, 4107772440, 4107772441, 4107772442, 4107772443, 4107772444, 4107772445, 4107772446, 4107772447, 4107772448, 4107772449, 4107772450, 4107772451, 4107772452, 4107772453, 4107772454, 4107772455, 4107772456, 4107772457, 4107772458, 4107772459, 4107772460, 4107772461, 4107772462, 4107772463, 4107772464, 4107772465, 4107772466, 4107772467, 4107772468, 4107772469, 4107772470, 4107772471, 4107772472, 4107772473, 4107772474, 4107772475, 4107772476, 4107772477, 4107772478, 4107772479, 4107772480, 4107772481, 4107772482, 4107772483, 4107772484, 4107772485, 4107772486, 4107772487, 4107772488, 4107772489, 4107772490, 4107772491, 4107772492, 4107772493, 4107772494, 4107772495, 4107772496, 4107772497, 4107772498, 4107772499, 4107772500, 4107772501], "tags": {"highway": "unclassified", "surface": "unpaved"}}, {"type": "way", "id": 410348550, "nodes": [4121774105, 4121774106, 4121774107, 4121774108, 4121774109, 4121774110, 4121774111, 4121774112, 4121774113, 4121774114, 4121774115, 4121774116, 4121774117, 4121774118, 4121774119, 4121774104, 4121774120, 4121774121, 4121774122, 4121774123, 4121774124, 4121774125, 4121774126, 4121774127, 4121774128, 4121774129, 4121774130, 4121774131, 4121774132, 4121774133, 4121774134, 4121774135, 4121774136, 4121774137, 4121774138, 4121774139, 4121774140, 4121774141, 4121774142, 4121774143, 4121774144, 4121774145, 4121774146, 3373306367], "tags": {"highway": "unclassified", "surface": "unpaved"}}, {"type": "way", "id": 435692255, "nodes": [4335884005, 4335884006], "tags": {"highway": "unclassified"}}, {"type": "way", "id": 443306573, "nodes": [3623819169, 4409117722, 4409117723, 4409117724, 4409117725, 4409117726, 4409117727, 4409117728, 4409117729, 4409117730, 4409117731, 4409117732, 4409117733, 4409117734, 4409117735, 4409117736, 4409117737, 4409117738, 4409117739, 4409117740, 4409117741, 4409117742, 4409117743, 4409117744, 4409117745, 4409117746, 4409117747, 4409117748, 4409117749, 4409117750, 4409117751, 4409117752, 4409117753, 4409117754, 4409117755, 4409117756, 4409117757, 4409117758, 4409117759, 4409117760, 4409117761, 4409117762, 4409117763, 4409117764, 4409117765, 4409117766, 4409117767, 4409117768, 4409117769, 4409117770, 4409117771, 4409117772], "tags": {"highway": "unclassified", "surface": "unpaved"}}, {"type": "way", "id": 443306579, "nodes": [4409117953, 3623819165, 4409117952, 4409117951, 3623819168, 3623819173, 3623819174, 3623819175, 3623819177, 3623819180, 3623819182, 3623819185, 3623819186, 3623819187, 3623819188], "tags": {"highway": "unclassified", "surface": "unpaved"}}, {"type": "way", "id": 530668997, "nodes": [3373306650, 5152603346, 3373306651, 3373306652, 3373306653, 8508849374, 8508849373, 8508849375, 8508849372, 3373306654, 8508849361, 8508849364, 3373306655, 8508849365, 8508849366, 3373306656, 8508849362, 3373306657, 3373306658, 8508849363, 3373306659, 3373306660, 3373306661, 3373306662, 8508849367, 8508849368, 8508849371, 3373306663, 8508849369, 8508849370, 3373306664, 3373306665, 8499399459, 8502639456, 8502639445, 3373306666, 8499399461, 8499399460, 3373306667, 8499399426, 3373306668, 8499399425, 8499399424, 8499399422, 8499399427, 8510215379, 8510215378, 8510215380, 8897871979, 3373306669, 8510215384, 8510215385, 8510215386, 8897871980, 3373306670, 3373306671, 8897871981, 3373306672, 8510215381, 8510215382, 8510215383, 3373306353], "tags": {"highway": "unclassified", "surface": "unpaved"}}, {"type": "way", "id": 563913443, "nodes": [8530734038, 5433855936, 8530734057, 5433855937, 5433855938, 8530734056, 8530734055, 5433855939, 8530734054, 5433855940, 8530734052, 8530734053, 5433855941, 8530734051, 8530734050, 5433855942, 5433855943, 5433855944, 8530734048, 8530734049, 5433855945, 8530734047, 5433855946, 5433855947, 5433855948, 8530734046, 5433855949, 8530734045, 8530734044, 5433855950, 5433855951, 8530734042, 8530734043, 8530734041, 5433855952, 5433855953, 8530734040, 5433855954, 8530734039, 5433855955], "tags": {"highway": "unclassified", "surface": "unpaved"}}, {"type": "way", "id": 563913450, "nodes": [5433855984, 4409117741], "tags": {"highway": "unclassified", "surface": "unpaved"}}, {"type": "way", "id": 618348798, "nodes": [5844691223, 5844691222, 5844691221, 5844691220, 5844691219, 5844691218, 5844691217, 5844691216, 5844691215, 5844691214, 5844691213, 5844691212], "tags": {"highway": "unclassified", "name": "Estrada Fazenda Santa Genoveva"}}, {"type": "way", "id": 737096320, "nodes": [6900757929, 6900757930], "tags": {"highway": "residential"}}, {"type": "way", "id": 737096321, "nodes": [6900757935, 6900757936], "tags": {"highway": "residential"}}, {"type": "way", "id": 737096322, "nodes": [6900757937, 6900757938], "tags": {"highway": "residential"}}, {"type": "way", "id": 737096323, "nodes": [6900757939, 6900757940], "tags": {"highway": "residential"}}, {"type": "way", "id": 776990720, "nodes": [2665850568, 3372695626, 321260475, 321260483, 6900757948, 321260485, 321260487, 321260488, 321260496, 4726127022, 321260498, 321260500, 321260501, 5844698754, 3372695638, 3372692674, 321260502, 321260503, 321260507, 3372695662, 4077294690, 321260509, 321260510, 7249975050], "tags": {"highway": "trunk", "lanes": "2", "maxspeed": "110", "maxspeed:bus": "80", "maxspeed:hgv": "80", "oneway": "no", "ref": "BR-471", "surface": "asphalt"}}, {"type": "way", "id": 776990723, "nodes": [7249975047, 4077294577, 4085213002, 3372692668, 4085213039, 4085213011, 4335884006], "tags": {"highway": "trunk", "lanes": "2", "maxspeed": "110", "maxspeed:bus": "80", "maxspeed:hgv": "80", "oneway": "no", "ref": "BR-471", "surface": "asphalt"}}, {"type": "way", "id": 776990724, "nodes": [7249975048, 7249975047], "tags": {"highway": "trunk", "lanes": "2", "maxspeed": "80", "oneway": "no", "ref": "BR-471", "surface": "asphalt"}}, {"type": "way", "id": 776990725, "nodes": [7249975049, 2665850570, 2665850586, 2665850606, 4077294701, 2665850614, 7249975048], "tags": {"highway": "trunk", "lanes": "2", "maxspeed": "60", "oneway": "no", "ref": "BR-471", "surface": "asphalt"}}, {"type": "way", "id": 776990727, "nodes": [7249975050, 7249975049], "tags": {"highway": "trunk", "lanes": "2", "maxspeed": "80", "oneway": "no", "ref": "BR-471", "surface": "asphalt"}}, {"type": "way", "id": 776990728, "nodes": [7249975052, 321260511, 321260512, 6900757947, 321260513, 321260514, 3372689514, 3372689551, 5844691223, 321260515, 3372689541, 6900757945, 321260516], "tags": {"highway": "trunk", "lanes": "2", "maxspeed": "110", "maxspeed:bus": "80", "maxspeed:hgv": "80", "oneway": "no", "ref": "BR-471", "surface": "asphalt"}}, {"type": "way", "id": 776990729, "nodes": [7249975051, 7249975052], "tags": {"highway": "trunk", "lanes": "2", "maxspeed": "80", "oneway": "no", "ref": "BR-471", "surface": "asphalt"}}, {"type": "way", "id": 776990730, "nodes": [4335884006, 7249975053], "tags": {"highway": "trunk", "lanes": "2", "maxspeed": "80", "oneway": "no", "ref": "BR-471", "surface": "asphalt"}}, {"type": "way", "id": 776990731, "nodes": [7249975053, 5375470154, 7249975051], "tags": {"highway": "trunk", "lanes": "2", "maxspeed": "60", "oneway": "no", "ref": "BR-471", "surface": "asphalt"}}, {"type": "way", "id": 914973565, "nodes": [8499399422, 8499399421, 8499358812, 8499399420, 8499399419, 8499399418, 8499358813, 8499399417, 8499358814, 8897871977, 8499358816, 8499358811, 8499358815], "tags": {"highway": "unclassified"}}, {"type": "way", "id": 914973566, "nodes": [8499399458, 8499399457, 8499399456, 8499399455, 8499399454, 8499399453, 8499399452, 8499399451, 8499399450, 8499399449, 8499399448, 8499399447, 8499399446, 8499399445, 8499399444, 8897871978, 8499399443, 8499399442, 8499399441, 8499399440, 8499399439, 8900892747, 8499399438, 8499399437, 8499399436, 8499399423, 8499399435, 8499399434, 8499399433, 8499399432, 8499399431, 8499399430, 8499399429, 8499399428, 8900892748, 8900892746, 8499399427], "tags": {"highway": "unclassified"}}, {"type": "way", "id": 915350898, "nodes": [8499399426, 8502579272, 8502579276, 8502579273, 8502579275, 8502579274], "tags": {"highway": "unclassified"}}, {"type": "way", "id": 915350899, "nodes": [8502579285, 8502579284, 8502579282, 8502579281, 8502579280, 8502579278, 8502579277, 3373306668], "tags": {"highway": "unclassified"}}, {"type": "way", "id": 915355947, "nodes": [8502639456, 8502639455, 8502639454, 8502639453, 8502639452, 8502639451, 8502639446, 8502639450, 8502639449, 8502639448, 8502639447], "tags": {"highway": "unclassified"}}]}